drftmpl
