Metadata-Version: 2.1
Name: drftmpl
Version: 0.0.2
Summary: Generate rest framework templates
Home-page: https://github.com/toyourheart163/drftmpl
Author: Mikele
Author-email: blive200@gmail.com
License: UNKNOWN
Platform: UNKNOWN
Classifier: Programming Language :: Python :: 3
Classifier: License :: OSI Approved :: MIT License
Classifier: Operating System :: OS Independent
Requires-Python: >=3.6
